.project
.pydevproject
AUTHORS
COPYING
ChangeLog
INSTALL
NEWS
README
TODO
ez_setup.py
setup.cfg
setup.py
docs/chimera.epydoc
docs/run-epydoc.sh
docs/examples/client.py
docs/examples/example.xml
docs/examples/minimo.py
docs/examples/proxy.py
docs/examples/server.py
docs/examples/site.xml
docs/examples/dome/dome-slit.log
docs/examples/dome/dome.log
docs/examples/dome/dometest.py
docs/examples/meade/meadedebug.py
docs/examples/meade/meadetest.py
docs/examples/meade/park-unpark.log
docs/examples/pec/lna-pec-accum.png
docs/examples/pec/lna-pec-accum.ps
docs/examples/pec/lna-pec-raw.png
docs/examples/pec/lna-pec-raw.ps
docs/examples/pec/meade-pec.txt
docs/examples/pec/meadepec.py
docs/examples/pec/pec.dec
docs/examples/pec/pec.gp
docs/examples/pec/pec.ra
docs/site/Makefile
docs/site/conf.py
docs/site/index.rst
docs/site/sync-sf.net
docs/site/templates/layout.html
src/chimera/__init__.py
src/chimera/controllers/__init__.py
src/chimera/controllers/autofocus.py
src/chimera/controllers/admin/__init__.py
src/chimera/controllers/admin/admin.py
src/chimera/controllers/console/TODO
src/chimera/controllers/console/__init__.py
src/chimera/controllers/console/command.py
src/chimera/controllers/console/commander.py
src/chimera/controllers/console/console.py
src/chimera/controllers/console/controller.py
src/chimera/controllers/console/message.py
src/chimera/controllers/console/namespace.py
src/chimera/controllers/console/commands/__init__.py
src/chimera/controllers/console/commands/alias.py
src/chimera/controllers/console/commands/object.py
src/chimera/controllers/console/commands/quit.py
src/chimera/controllers/console/commands/site.py
src/chimera/controllers/console/commands/unalias.py
src/chimera/controllers/console/doc/use-cases.txt
src/chimera/controllers/scheduler/__init__.py
src/chimera/controllers/scheduler/blocks.py
src/chimera/controllers/scheduler/clock.py
src/chimera/controllers/scheduler/constraints.py
src/chimera/controllers/scheduler/create-tables.py
src/chimera_python.egg-info/PKG-INFO
src/chimera_python.egg-info/SOURCES.txt
src/chimera_python.egg-info/dependency_links.txt
src/chimera_python.egg-info/requires.txt
src/chimera_python.egg-info/top_level.txt
src/chimera_python.egg-info/zip-safe
