Metadata-Version: 1.0
Name: chimera-python
Version: 0.1
Summary: Chimera - Observatory Automation System
Home-page: http://chimera.sf.net
Author: P. Henrique Silva
Author-email: henrique@astro.ufsc.br
License: GPLv2
Download-URL: http://chimera.googlecode.com/svn/trunk#egg=chimera-dev
Platform: GNU/Linux
Classifier: Development Status :: 3 - Alpha
Classifier: Environment :: Console
Classifier: Intended Audience :: Science/Research
Classifier: Intended Audience :: End Users/Desktop
Classifier: Intended Audience :: Developers
Classifier: License :: OSI Approved :: GNU General Public License (GPL)
Classifier: Natural Language :: English
Classifier: Natural Language :: Portuguese (Brazilian)
Classifier: Operating System :: POSIX :: Linux
Classifier: Programming Language :: Python
Classifier: Topic :: Scientific/Engineering :: Astronomy
